srx_lib_azure/__init__.py
srx_lib_azure/blob.py
srx_lib_azure/document.py
srx_lib_azure/email.py
srx_lib_azure/speech.py
srx_lib_azure/table.py
srx_lib_azure-0.4.3.dist-info/METADATA
srx_lib_azure-0.4.3.dist-info/WHEEL
srx_lib_azure-0.4.3.dist-info/RECORD
