Metadata-Version: 2.4
Name: srx-lib-azure
Version: 0.4.3
Summary: Azure helpers for SRX services: Blob, Email, Table, Document Intelligence, Speech Services
Author-email: SRX <dev@srx.id>
Requires-Python: >=3.12
Requires-Dist: azure-ai-documentintelligence>=1.0.0
Requires-Dist: azure-communication-email>=1.0.0
Requires-Dist: azure-data-tables>=12.7.0
Requires-Dist: azure-storage-blob>=12.22.0
Provides-Extra: all
Requires-Dist: azure-ai-documentintelligence>=1.0.0; extra == 'all'
Requires-Dist: azure-cognitiveservices-speech>=1.41.1; extra == 'all'
Provides-Extra: document
Requires-Dist: azure-ai-documentintelligence>=1.0.0; extra == 'document'
Provides-Extra: speech
Requires-Dist: azure-cognitiveservices-speech>=1.41.1; extra == 'speech'
